RenRen_Shop/__init__.py
RenRen_Shop/MyLog/error.log
RenRen_Shop/api/RenRen_api.py
RenRen_Shop/api/__init__.py
RenRen_Shop/api/app/MySecKill.py
RenRen_Shop/api/app/__init__.py
RenRen_Shop/api/app/del_bug.py
RenRen_Shop/api/app/goods_to_csv.py
RenRen_Shop/api/app/mass_update_goods.py
RenRen_Shop/api/application/__init__.py
RenRen_Shop/api/application/diypage/__init__.py
RenRen_Shop/api/application/diypage/page_add.py
RenRen_Shop/api/application/diypage/page_content.py
RenRen_Shop/api/application/diypage/page_edit.py
RenRen_Shop/api/application/diypage/page_infos.py
RenRen_Shop/api/application/diypage/template/content_template.json
RenRen_Shop/api/application/diypage/template/page_infos_template.json
RenRen_Shop/api/application/diypage/template/seckill_content_template.json
RenRen_Shop/api/application/goods_helper/__init__.py
RenRen_Shop/api/application/goods_helper/goods_helper.py
RenRen_Shop/api/application/seckill/__init__.py
RenRen_Shop/api/application/seckill/add.py
RenRen_Shop/api/application/seckill/delete.py
RenRen_Shop/api/application/seckill/edit.py
RenRen_Shop/api/application/seckill/fetch_list.py
RenRen_Shop/api/application/seckill/infos.py
RenRen_Shop/api/application/seckill/template/add_seckill_template.json
RenRen_Shop/api/application/seckill/template/goods_info.json
RenRen_Shop/api/application/seckill/template/seckill_info_template.json
RenRen_Shop/api/category/__init__.py
RenRen_Shop/api/category/category_list.py
RenRen_Shop/api/category/set_category.py
RenRen_Shop/api/commission/__init__.py
RenRen_Shop/api/commission/change_agent.py
RenRen_Shop/api/commission/fetch_agent_list.py
RenRen_Shop/api/commission/fetch_commission_goods_list.py
RenRen_Shop/api/commission/goods_commission.py
RenRen_Shop/api/goods/__init__.py
RenRen_Shop/api/goods/add_goods.py
RenRen_Shop/api/goods/edit_goods.py
RenRen_Shop/api/goods/fetch_goodsId_list_by_filter.py
RenRen_Shop/api/goods/fetch_goods_list.py
RenRen_Shop/api/goods/filter_goods.py
RenRen_Shop-1.0.7.dist-info/LICENSE
RenRen_Shop-1.0.7.dist-info/METADATA
RenRen_Shop-1.0.7.dist-info/WHEEL
RenRen_Shop-1.0.7.dist-info/top_level.txt
RenRen_Shop-1.0.7.dist-info/RECORD
