Metadata-Version: 2.1
Name: RenRen-Shop
Version: 1.0.7
Summary: 人人商城后台管理
Author: YarnBlue
Author-email: zqb090325@126.com
License: MIT
Platform: UNKNOWN
License-File: LICENSE
